Metadata-Version: 2.1
Name: vxinaay-xnrpc
Version: 1.2.2
Summary: simple rpc based on zerorpc and gevent
Home-page: https://github.com/yidao620c/xnrpc
Author: jac lin
Author-email: vxinaay@gmail.com
License: MIT
Keywords: xnrpc,gevent,zerorpc,subprocess
Platform: UNKNOWN
Classifier: Development Status :: 4 - Beta
Classifier: Intended Audience :: Developers
Classifier: Topic :: Software Development :: Build Tools
Classifier: License :: OSI Approved :: MIT License
Classifier: Programming Language :: Python :: 2.6
Classifier: Programming Language :: Python :: 2.7
Classifier: Programming Language :: Python :: 3
Classifier: Programming Language :: Python :: 3.3
Classifier: Programming Language :: Python :: 3.4
Classifier: Programming Language :: Python :: 3.5
Requires-Dist: gevent (>=1.1.2)
Requires-Dist: zerorpc (>=0.6.0)
